pyrabola/__init__.py
pyrabola/__main__.py
pyrabola/beam_injection.py
pyrabola/parser.py
pyrabola/propagate.py
pyrabola/util.py
pyrabola/beams/__init__.py
pyrabola/beams/beams.py
pyrabola/beams/fresnel_gouy.py
pyrabola/beams/frft.py
pyrabola/beams/geometric.py
pyrabola/beams/hermite.py
pyrabola/elements/__init__.py
pyrabola/elements/camera.py
pyrabola/elements/mirror.py
pyrabola/elements/parabola.py
pyrabola/propagators/__init__.py
pyrabola/propagators/hermite.py
pyrabola/propagators/plotting.py
pyrabola-0.0.3.dist-info/LICENSE
pyrabola-0.0.3.dist-info/METADATA
pyrabola-0.0.3.dist-info/WHEEL
pyrabola-0.0.3.dist-info/top_level.txt
pyrabola-0.0.3.dist-info/RECORD
