Metadata-Version: 2.1
Name: pyrabola
Version: 0.0.3
Summary: Simulate laser propagation through a system of planar and focussing mirrors
Home-page: https://github.com/unpairedbracket/pyrabola
Author: Ben Spiers
Author-email: info@benspiers.co.uk
License: UNKNOWN
Project-URL: Bug Tracker, https://github.com/unpairedbracket/pyrabola/issues
Platform: UNKNOWN
Classifier: Programming Language :: Python :: 3
Classifier: License :: OSI Approved :: MIT License
Classifier: Operating System :: OS Independent
Requires-Python: >=3.6
License-File: LICENSE
Requires-Dist: numpy
Requires-Dist: scipy
Requires-Dist: matplotlib
Requires-Dist: tomli
